{
"미친": "[STRONG_NEG]",
"개지랄": "[PROFANITY]",
"뭣같": "[PROFANITY]",
"쳐": "[PROFANITY]",
"ㅅㅂ": "[PROFANITY]",
"짱나": "[STRONG_NEG]",
"뒤지기싫으면": "[THREAT]",
"좆같": "[PROFANITY]",
"개짜증": "[STRONG_NEG]",
"씨발새끼야": "[PROFANITY]",
"씨바련": "[PROFANITY]",
"개새키": "[PROFANITY]",
"개병신": "[PROFANITY]",
"븅신": "[PROFANITY]",
"ㅂㅅ": "[PROFANITY]",
"시발년": "[PROFANITY]",
"좆박": "[PROFANITY]",
"ㅐ씨발": "[PROFANITY]",
"씨발": "[PROFANITY]",
"병신": "[PROFANITY]",
"ㄱ ㅐㅂ신": "[PROFANITY]",
"ㄱ ㅐ 조옷 ㅂ ㅣ응신": "[PROFANITY]",
"개좆": "[PROFANITY]",
"씨빠거": "[PROFANITY]",
"애미": "[PROFANITY]",
"지 ㅈ대로": "[CONTEMPT]",
"카악퉤": "[CONTEMPT]",
"ㅉㅉ": "[CONTEMPT]",
"ㅉ": "[CONTEMPT]",
"꺼져": "[THREAT]"
}
